odoo/addons/l10n_ec_credit_note/README.rst
odoo/addons/l10n_ec_credit_note/__init__.py
odoo/addons/l10n_ec_credit_note/__manifest__.py
odoo/addons/l10n_ec_credit_note/i18n/es_EC.po
odoo/addons/l10n_ec_credit_note/i18n/l10n_ec_credit_note.pot
odoo/addons/l10n_ec_credit_note/models/__init__.py
odoo/addons/l10n_ec_credit_note/models/account_move.py
odoo/addons/l10n_ec_credit_note/models/account_move_line.py
odoo/addons/l10n_ec_credit_note/models/product_category.py
odoo/addons/l10n_ec_credit_note/models/product_template.py
odoo/addons/l10n_ec_credit_note/models/res_company.py
odoo/addons/l10n_ec_credit_note/models/res_config.py
odoo/addons/l10n_ec_credit_note/readme/CONTRIBUTORS.md
odoo/addons/l10n_ec_credit_note/readme/DESCRIPTION.md
odoo/addons/l10n_ec_credit_note/static/description/icon.png
odoo/addons/l10n_ec_credit_note/static/description/index.html
odoo/addons/l10n_ec_credit_note/tests/__init__.py
odoo/addons/l10n_ec_credit_note/tests/test_l10n_ec_edi_credit_note.py
odoo/addons/l10n_ec_credit_note/views/account_move_view.xml
odoo/addons/l10n_ec_credit_note/views/product_category_view.xml
odoo/addons/l10n_ec_credit_note/views/product_template_view.xml
odoo/addons/l10n_ec_credit_note/views/res_config_view.xml
odoo/addons/l10n_ec_credit_note/wizard/__init__.py
odoo/addons/l10n_ec_credit_note/wizard/account_invoice_refund_view.xml
odoo/addons/l10n_ec_credit_note/wizard/account_move_reversal.py
odoo_addon_l10n_ec_credit_note-17.0.1.0.0.3.dist-info/METADATA
odoo_addon_l10n_ec_credit_note-17.0.1.0.0.3.dist-info/WHEEL
odoo_addon_l10n_ec_credit_note-17.0.1.0.0.3.dist-info/top_level.txt
odoo_addon_l10n_ec_credit_note-17.0.1.0.0.3.dist-info/RECORD
