Metadata-Version: 2.1
Name: odoo-addon-l10n_ec_credit_note
Version: 17.0.1.0.0.3
Requires-Python: >=3.10
Requires-Dist: odoo-addon-l10n_ec_account_edi>=17.0dev,<17.1dev
Requires-Dist: odoo-addon-l10n_ec_base>=17.0dev,<17.1dev
Requires-Dist: odoo>=17.0a,<17.1dev
Summary: Credit Notes extension for Ecuador
Home-page: https://github.com/OCA/l10n-ecuador
License: AGPL-3
Author: Odoo Community Association (OCA), Odoo-EC
Author-email: support@odoo-community.org
Classifier: Programming Language :: Python
Classifier: Framework :: Odoo
Classifier: Framework :: Odoo :: 17.0
Classifier: License :: OSI Approved :: GNU Affero General Public License v3
